{
    "entityNumberCounter": 20,
    "entities": [
        {
            "hierarchyOrder": 6.0,
            "name": "Cube Entity",
            "uniqueNumber": 12,
            "parent": -1,
            "exposed": false,
            "collapsedChildren": false,
            "components": [
                {
                    "name": "transform",
                    "specifics": "{\"pos\":{\"x\":13.25,\"y\":2.5,\"z\":2.5},\"rot\":{\"x\":0.0,\"y\":0.0,\"z\":0.0,\"w\":1.0},\"scale\":{\"x\":0.5680000185966492,\"y\":0.45399999618530276,\"z\":0.9780001640319824}}"
                },
                {
                    "name": "GLTFShape",
                    "specifics": "{\"assetID\":\"2ac88f39-e110-4b96-82de-c73f1d0d3355\"}"
                }
            ]
        },
        {
            "hierarchyOrder": 5.0,
            "name": "Cube Entity",
            "uniqueNumber": 13,
            "parent": -1,
            "exposed": false,
            "collapsedChildren": false,
            "components": [
                {
                    "name": "transform",
                    "specifics": "{\"pos\":{\"x\":13.25,\"y\":2.5,\"z\":9.5},\"rot\":{\"x\":0.0,\"y\":0.0,\"z\":0.0,\"w\":1.0},\"scale\":{\"x\":3.0,\"y\":1.0,\"z\":3.0}}"
                },
                {
                    "name": "boxShape",
                    "specifics": ""
                }
            ]
        },
        {
            "hierarchyOrder": 4.0,
            "name": "Cube Entity",
            "uniqueNumber": 14,
            "parent": -1,
            "exposed": false,
            "collapsedChildren": false,
            "components": [
                {
                    "name": "transform",
                    "specifics": "{\"pos\":{\"x\":6.5,\"y\":2.5,\"z\":9.5},\"rot\":{\"x\":0.0,\"y\":0.0,\"z\":0.0,\"w\":1.0},\"scale\":{\"x\":3.0,\"y\":1.0,\"z\":3.0}}"
                },
                {
                    "name": "boxShape",
                    "specifics": ""
                }
            ]
        },
        {
            "hierarchyOrder": 1.0,
            "name": "Cube Entity",
            "uniqueNumber": 15,
            "parent": -1,
            "exposed": false,
            "collapsedChildren": false,
            "components": [
                {
                    "name": "transform",
                    "specifics": "{\"pos\":{\"x\":6.5,\"y\":5.25,\"z\":6.0},\"rot\":{\"x\":0.0,\"y\":0.0,\"z\":0.0,\"w\":1.0},\"scale\":{\"x\":7.0,\"y\":10.5,\"z\":0.5}}"
                },
                {
                    "name": "boxShape",
                    "specifics": ""
                }
            ]
        },
        {
            "hierarchyOrder": 2.0,
            "name": "Docks Module Stairs 01",
            "uniqueNumber": 17,
            "parent": -1,
            "exposed": false,
            "collapsedChildren": false,
            "components": [
                {
                    "name": "transform",
                    "specifics": "{\"pos\":{\"x\":2.25,\"y\":-0.25,\"z\":2.75},\"rot\":{\"x\":0.0,\"y\":-0.7071065902709961,\"z\":0.0,\"w\":0.7071070671081543},\"scale\":{\"x\":1.0,\"y\":1.2493398189544678,\"z\":1.0}}"
                },
                {
                    "name": "GLTFShape",
                    "specifics": "{\"assetID\":\"ea672e8c-ab8d-480a-86ec-f0de406f8e57\"}"
                }
            ]
        },
        {
            "hierarchyOrder": 0.0,
            "name": "Docks Module Stairs 01",
            "uniqueNumber": 18,
            "parent": -1,
            "exposed": false,
            "collapsedChildren": false,
            "components": [
                {
                    "name": "transform",
                    "specifics": "{\"pos\":{\"x\":4.22011137008667,\"y\":0.6775649785995483,\"z\":2.75},\"rot\":{\"x\":0.0,\"y\":-0.7071065902709961,\"z\":0.0,\"w\":0.7071070671081543},\"scale\":{\"x\":1.0,\"y\":1.2493398189544678,\"z\":1.0}}"
                },
                {
                    "name": "GLTFShape",
                    "specifics": "{\"assetID\":\"ea672e8c-ab8d-480a-86ec-f0de406f8e57\"}"
                }
            ]
        },
        {
            "hierarchyOrder": 3.0,
            "name": "Docks Module Stairs 01",
            "uniqueNumber": 19,
            "parent": -1,
            "exposed": false,
            "collapsedChildren": false,
            "components": [
                {
                    "name": "transform",
                    "specifics": "{\"pos\":{\"x\":6.122581481933594,\"y\":1.5920236110687256,\"z\":2.750000238418579},\"rot\":{\"x\":0.0,\"y\":-0.7071065902709961,\"z\":0.0,\"w\":0.7071070671081543},\"scale\":{\"x\":1.0,\"y\":1.2493398189544678,\"z\":1.0}}"
                },
                {
                    "name": "GLTFShape",
                    "specifics": "{\"assetID\":\"ea672e8c-ab8d-480a-86ec-f0de406f8e57\"}"
                }
            ]
        }
    ]
}
